{"ticker": "AVGO", "days": 120, "data": [{"date": "2026-03-09", "close_price": 344.4810485839844, "score": 0.0, "s_force": 0.7784789054551579, "s_div": -0.07465002652440537, "s_conc": 0.0, "er": null, "atr_pct": null}, {"date": "2026-03-10", "close_price": 341.3226623535156, "score": 0.0, "s_force": -0.41994922539808177, "s_div": 0.0, "s_conc": 0.0, "er": null, "atr_pct": null}, {"date": "2026-03-11", "close_price": 340.3163757324219, "score": 0.0, "s_force": -0.2754874520879947, "s_div": 0.0, "s_conc": 0.0, "er": null, "atr_pct": null}, {"date": "2026-03-12", "close_price": 334.7369384765625, "score": 0.0, "s_force": -0.3974514588776555, "s_div": 0.0, "s_conc": 0.0, "er": null, "atr_pct": null}, {"date": "2026-03-13", "close_price": 320.9776306152344, "score": 0.0, "s_force": -0.729746982677207, "s_div": 0.0, "s_conc": 0.0, "er": null, "atr_pct": null}, {"date": "2026-03-16", "close_price": 323.7275085449219, "score": 0.40745935836632574, "s_force": 0.2990056096581167, "s_div": 0.5552508827848711, "s_conc": 0.0, "er": null, "atr_pct": null}, {"date": "2026-03-17", "close_price": 320.1307373046875, "score": 0.0, "s_force": -0.18923481680655005, "s_div": 0.7745668298062629, "s_conc": 0.0, "er": null, "atr_pct": null}, {"date": "2026-03-18", "close_price": 314.7704772949219, "score": 0.0, "s_force": -0.20035184725905963, "s_div": 1.0, "s_conc": 0.0, "er": null, "atr_pct": null}, {"date": "2026-03-19", "close_price": 318.6661376953125, "score": 0.3757464999511885, "s_force": 0.18294516355766294, "s_div": 0.771736347001422, "s_conc": 0.0, "er": null, "atr_pct": null}, {"date": "2026-03-20", "close_price": 309.3703918457031, "score": 0.0, "s_force": -0.6779241395999691, "s_div": 1.0, "s_conc": 0.0, "er": null, "atr_pct": null}, {"date": "2026-03-23", "close_price": 322.0003967285156, "score": 0.5050115824122302, "s_force": 0.3985998426071583, "s_div": 0.6398314076151236, "s_conc": 0.0, "er": null, "atr_pct": null}, {"date": "2026-03-24", "close_price": 317.78704833984375, "score": 0.0, "s_force": -0.18118538325906436, "s_div": 0.05822469414836273, "s_conc": 0.0, "er": null, "atr_pct": null}, {"date": "2026-03-25", "close_price": 318.30621337890625, "score": 0.07997502024120878, "s_force": 0.019489465307971472, "s_div": 0.3281774928923113, "s_conc": 0.0, "er": null, "atr_pct": null}, {"date": "2026-03-26", "close_price": 308.9310607910156, "score": 0.0, "s_force": -0.23491276459492155, "s_div": 0.042437175367653644, "s_conc": 0.0, "er": null, "atr_pct": null}, {"date": "2026-03-27", "close_price": 300.2048645019531, "score": 0.0, "s_force": -0.1117972444954086, "s_div": 0.3888660196213905, "s_conc": 0.0, "er": null, "atr_pct": null}, {"date": "2026-03-30", "close_price": 292.94635009765625, "score": 0.13254132547340922, "s_force": 0.018809655585455453, "s_div": 0.9339460192897957, "s_conc": 0.0, "er": null, "atr_pct": null}, {"date": "2026-03-31", "close_price": 309.02093505859375, "score": 0.6337811485176817, "s_force": 1.0, "s_div": 0.40167854421639176, "s_conc": 0.0, "er": null, "atr_pct": null}, {"date": "2026-04-01", "close_price": 312.99462890625, "score": 0.0, "s_force": 0.2592977869283338, "s_div": 0.0, "s_conc": 0.0, "er": null, "atr_pct": null}, {"date": "2026-04-02", "close_price": 314.0529479980469, "score": 0.0, "s_force": 0.07819246372774452, "s_div": 0.0, "s_conc": 0.0, "er": null, "atr_pct": null}, {"date": "2026-04-06", "close_price": 313.9331359863281, "score": -0.015579084278927242, "s_force": -0.006203832870953229, "s_div": -0.03912224458951704, "s_conc": 0.0, "er": null, "atr_pct": null}, {"date": "2026-04-07", "close_price": 333.4422607421875, "score": 0.0, "s_force": 1.0, "s_div": 0.0, "s_conc": 0.0, "er": null, "atr_pct": null}, {"date": "2026-04-08", "close_price": 350.0759582519531, "score": 0.0, "s_force": 0.37711531287838385, "s_div": 0.0, "s_conc": 0.0, "er": null, "atr_pct": null}, {"date": "2026-04-09", "close_price": 354.34918212890625, "score": 0.0, "s_force": -0.3156088138076512, "s_div": 0.0, "s_conc": 0.0, "er": null, "atr_pct": null}, {"date": "2026-04-10", "close_price": 370.9628601074219, "score": 0.0, "s_force": 0.25245168610221685, "s_div": -0.625355191071252, "s_conc": 0.0, "er": null, "atr_pct": null}, {"date": "2026-04-13", "close_price": 379.1499328613281, "score": -0.5577561206091575, "s_force": -0.31109189007697696, "s_div": -1.0, "s_conc": 0.0, "er": null, "atr_pct": null}, {"date": "2026-04-14", "close_price": 380.17828369140625, "score": -0.7932429485132324, "s_force": -0.6292343753659667, "s_div": -1.0, "s_conc": 0.0, "er": null, "atr_pct": null}, {"date": "2026-04-15", "close_price": 396.0931091308594, "score": 0.0, "s_force": 0.2177036026847536, "s_div": -1.0, "s_conc": 0.0, "er": null, "atr_pct": null}, {"date": "2026-04-16", "close_price": 397.8403625488281, "score": -0.6356900610158029, "s_force": -0.4041018536742752, "s_div": -1.0, "s_conc": 0.0, "er": null, "atr_pct": null}, {"date": "2026-04-17", "close_price": 405.8976135253906, "score": -0.37868731537382055, "s_force": -0.14340408282503142, "s_div": -1.0, "s_conc": 0.0, "er": null, "atr_pct": null}, {"date": "2026-04-20", "close_price": 398.9985046386719, "score": -0.7589965445175338, "s_force": -0.5760757545895567, "s_div": -1.0, "s_conc": 0.0, "er": null, "atr_pct": null}, {"date": "2026-04-21", "close_price": 401.5345153808594, "score": -0.4158983640087406, "s_force": -0.1729714491851469, "s_div": -1.0, "s_conc": 0.0, "er": null, "atr_pct": null}, {"date": "2026-04-22", "close_price": 421.98211669921875, "score": 0.0, "s_force": 0.557390201785579, "s_div": -0.8014587748874469, "s_conc": 0.0, "er": null, "atr_pct": null}, {"date": "2026-04-23", "close_price": 419.27642822265625, "score": -0.6457747539906797, "s_force": -0.478681112133144, "s_div": -0.8711959221314093, "s_conc": 0.0, "er": null, "atr_pct": null}, {"date": "2026-04-24", "close_price": 422.09197998046875, "score": -0.3584713344053949, "s_force": -0.15256785043704643, "s_div": -0.8422593437757563, "s_conc": 0.0, "er": null, "atr_pct": null}, {"date": "2026-04-27", "close_price": 417.5391845703125, "score": -0.5831774014704925, "s_force": -0.3400958815858759, "s_div": -1.0, "s_conc": 0.0, "er": null, "atr_pct": null}, {"date": "2026-04-28", "close_price": 399.19818115234375, "score": -0.8331635160814529, "s_force": -0.7866222648467514, "s_div": -0.8824584245202428, "s_conc": 0.0, "er": null, "atr_pct": null}, {"date": "2026-04-29", "close_price": 404.809326171875, "score": 0.0, "s_force": 0.14001330699304224, "s_div": -1.0, "s_conc": 0.0, "er": null, "atr_pct": null}, {"date": "2026-04-30", "close_price": 416.7703857421875, "score": 0.0, "s_force": 0.3652013990900952, "s_div": -0.6102238078743359, "s_conc": 0.0, "er": null, "atr_pct": null}, {"date": "2026-05-01", "close_price": 420.6142883300781, "score": 0.0, "s_force": 0.049606403456679125, "s_div": -0.8189628357276179, "s_conc": 0.0, "er": null, "atr_pct": null}, {"date": "2026-05-04", "close_price": 415.84185791015625, "score": -0.3081620429955541, "s_force": -0.19896713264341395, "s_div": -0.477284079443345, "s_conc": 0.0, "er": null, "atr_pct": null}, {"date": "2026-05-05", "close_price": 426.6846923828125, "score": 0.0, "s_force": 0.4794947107913865, "s_div": -0.8283285110959278, "s_conc": 0.0, "er": null, "atr_pct": null}, {"date": "2026-05-06", "close_price": 424.7677307128906, "score": -0.4050938313342964, "s_force": -0.24163347205854951, "s_div": -0.6791319546380418, "s_conc": 0.0, "er": null, "atr_pct": null}, {"date": "2026-05-07", "close_price": 411.9080810546875, "score": -0.42679449209203985, "s_force": -0.7297741355796936, "s_div": -0.24960262305735073, "s_conc": 0.0, "er": null, "atr_pct": null}, {"date": "2026-05-08", "close_price": 429.3205261230469, "score": 0.0, "s_force": 1.0, "s_div": -0.500636436658832, "s_conc": 0.0, "er": null, "atr_pct": null}, {"date": "2026-05-11", "close_price": 427.75299072265625, "score": -0.14391109088357823, "s_force": -0.042501855294378894, "s_div": -0.48728230652181853, "s_conc": 0.0, "er": null, "atr_pct": null}, {"date": "2026-05-12", "close_price": 418.6374206542969, "score": -0.3563581420687614, "s_force": -0.3349266617956259, "s_div": -0.3791609922538511, "s_conc": 0.0, "er": null, "atr_pct": null}, {"date": "2026-05-13", "close_price": 416.13140869140625, "score": 0.0, "s_force": 0.026831551837779778, "s_div": -0.4347581232601818, "s_conc": 0.0, "er": null, "atr_pct": null}, {"date": "2026-05-14", "close_price": 439.0950622558594, "score": 0.0, "s_force": 1.0, "s_div": -0.18590639342130375, "s_conc": 0.0, "er": null, "atr_pct": null}, {"date": "2026-05-15", "close_price": 424.51812744140625, "score": -0.36735096496512554, "s_force": -0.8075768413952109, "s_div": -0.16710079405901243, "s_conc": 0.0, "er": null, "atr_pct": null}, {"date": "2026-05-18", "close_price": 420.0451965332031, "score": -0.09777426840063537, "s_force": -0.16921100080769894, "s_div": -0.05649637148676756, "s_conc": 0.0, "er": null, "atr_pct": null}, {"date": "2026-05-19", "close_price": 410.4204406738281, "score": 0.0, "s_force": -0.31158843213619664, "s_div": 0.0, "s_conc": 0.0, "er": null, "atr_pct": null}, {"date": "2026-05-20", "close_price": 417.0998840332031, "score": 0.0, "s_force": 0.34357693798714467, "s_div": 0.0, "s_conc": 0.0, "er": null, "atr_pct": null}, {"date": "2026-05-21", "close_price": 413.9149169921875, "score": 0.0, "s_force": -0.11271921039008656, "s_div": 0.0, "s_conc": 0.0, "er": null, "atr_pct": null}, {"date": "2026-05-22", "close_price": 413.485595703125, "score": 0.0, "s_force": 0.01985675213813766, "s_div": -0.3926260679932567, "s_conc": 0.0, "er": null, "atr_pct": null}, {"date": "2026-05-26", "close_price": 421.3431701660156, "score": 0.0, "s_force": 0.41354061377166107, "s_div": 0.0, "s_conc": 0.0, "er": null, "atr_pct": null}, {"date": "2026-05-27", "close_price": 421.193359375, "score": 0.0, "s_force": -0.050244287876293196, "s_div": 0.0, "s_conc": 0.0, "er": null, "atr_pct": null}, {"date": "2026-05-28", "close_price": 425.9059143066406, "score": 0.0, "s_force": 0.15543180719528, "s_div": 0.0, "s_conc": 0.0, "er": null, "atr_pct": null}, {"date": "2026-05-29", "close_price": 446.06402587890625, "score": 0.0, "s_force": 1.0, "s_div": 0.0, "s_conc": 0.0, "er": null, "atr_pct": null}, {"date": "2026-06-01", "close_price": 459.2431640625, "score": 0.5431554221959018, "s_force": 0.29501781266080834, "s_div": 1.0, "s_conc": 0.0, "er": null, "atr_pct": null}, {"date": "2026-06-02", "close_price": 480.8090515136719, "score": 0.6240690892455156, "s_force": 0.5504637766996331, "s_div": 0.7075165426629734, "s_conc": 0.0, "er": null, "atr_pct": null}, {"date": "2026-06-03", "close_price": 478.4727478027344, "score": 0.0, "s_force": -0.4848578718441824, "s_div": 0.0, "s_conc": 0.0, "er": null, "atr_pct": null}, {"date": "2026-06-04", "close_price": 418.248046875, "score": 0.0, "s_force": -1.0, "s_div": 0.0, "s_conc": 0.0, "er": null, "atr_pct": null}, {"date": "2026-06-05", "close_price": 385.1204833984375, "score": 0.0, "s_force": -0.4620062119607002, "s_div": 0.0, "s_conc": 0.0, "er": null, "atr_pct": null}, {"date": "2026-06-08", "close_price": 395.9732971191406, "score": 0.0, "s_force": 1.0, "s_div": 0.0, "s_conc": 0.0, "er": null, "atr_pct": null}, {"date": "2026-06-09", "close_price": 391.5403137207031, "score": 0.4982528274481751, "s_force": 0.2493498934945973, "s_div": 0.9956125369890322, "s_conc": 0.0, "er": null, "atr_pct": null}, {"date": "2026-06-10", "close_price": 371.51202392578125, "score": 0.0, "s_force": -0.4614971502330844, "s_div": 0.8963669881889516, "s_conc": 0.0, "er": null, "atr_pct": null}, {"date": "2026-06-11", "close_price": 384.9607238769531, "score": 0.7691278904526536, "s_force": 0.7210033953777251, "s_div": 0.8204645299378086, "s_conc": 0.0, "er": null, "atr_pct": null}, {"date": "2026-06-12", "close_price": 381.4662780761719, "score": 0.0, "s_force": -0.04713804049293797, "s_div": 0.525399505043716, "s_conc": 0.0, "er": null, "atr_pct": null}, {"date": "2026-06-15", "close_price": 393.3175048828125, "score": 0.42176819235119145, "s_force": 0.30417970197028604, "s_div": 0.5848135392563728, "s_conc": 0.0, "er": null, "atr_pct": null}, {"date": "2026-06-16", "close_price": 376.1147155761719, "score": 0.0, "s_force": -0.6548416769449767, "s_div": 0.6881041029583344, "s_conc": 0.0, "er": null, "atr_pct": null}, {"date": "2026-06-17", "close_price": 392.2791442871094, "score": 0.6032762909889388, "s_force": 0.5524506399254889, "s_div": 0.6587779196318008, "s_conc": 0.0, "er": null, "atr_pct": null}, {"date": "2026-06-18", "close_price": 410.70001220703125, "score": 0.5412900962676479, "s_force": 0.2929949683174395, "s_div": 1.0, "s_conc": 0.0, "er": null, "atr_pct": null}, {"date": "2026-06-22", "close_price": 392.1300048828125, "score": 0.0, "s_force": -0.5777659517730073, "s_div": 0.42618070057608576, "s_conc": 0.0, "er": null, "atr_pct": null}, {"date": "2026-06-23", "close_price": 380.1499938964844, "score": 0.0, "s_force": -0.3096582498715424, "s_div": 0.8973983583458819, "s_conc": 0.0, "er": null, "atr_pct": null}, {"date": "2026-06-24", "close_price": 382.07000732421875, "score": 0.0, "s_force": -0.0011973237174039012, "s_div": 0.3953393474928637, "s_conc": 0.0, "er": null, "atr_pct": null}, {"date": "2026-06-25", "close_price": 378.9100036621094, "score": 0.0, "s_force": -0.14301728529978616, "s_div": 0.4246453114309183, "s_conc": 0.0, "er": null, "atr_pct": null}, {"date": "2026-06-26", "close_price": 365.0199890136719, "score": 0.0, "s_force": -0.3801849076803373, "s_div": 0.8788612410268941, "s_conc": 0.0, "er": null, "atr_pct": null}, {"date": "2026-06-29", "close_price": 372.45001220703125, "score": 0.10334652132178104, "s_force": 0.04999318982270864, "s_div": 0.21363916779844858, "s_conc": 0.0, "er": null, "atr_pct": null}, {"date": "2026-06-30", "close_price": 377.75, "score": 0.0, "s_force": -0.05561099095485113, "s_div": 0.459227910276413, "s_conc": 0.0, "er": null, "atr_pct": null}, {"date": "2026-07-01", "close_price": 369.3399963378906, "score": 0.0, "s_force": -0.29575058401182647, "s_div": 0.47451035792504936, "s_conc": 0.0, "er": null, "atr_pct": null}, {"date": "2026-07-02", "close_price": 360.45001220703125, "score": 0.0, "s_force": -0.2251421601819526, "s_div": 0.9387317188512193, "s_conc": 0.0, "er": null, "atr_pct": null}, {"date": "2026-07-06", "close_price": 373.8999938964844, "score": 0.3229709563524776, "s_force": 0.21879981500750867, "s_div": 0.4767382396719774, "s_conc": 0.0, "er": null, "atr_pct": null}, {"date": "2026-07-07", "close_price": 370.7799987792969, "score": 0.0, "s_force": -0.1621660732523178, "s_div": 0.21678411169750159, "s_conc": 0.0, "er": null, "atr_pct": null}], "signals": [{"date": "2026-06-11", "signal_type": "bottom", "entry_price": 385.57000732421875, "s_force": 0.6828211717476275, "peak_val": 0.7274020293455201, "signal_tier": "CONFIRMED", "action_pct": 1.0, "market_regime": "UNKNOWN", "direction": "LONG"}, {"date": "2026-06-29", "signal_type": "bottom", "entry_price": 372.45001220703125, "s_force": 0.040597867478454015, "peak_val": 0.09106195815342827, "signal_tier": "CONFIRMED", "action_pct": 1.0, "market_regime": "UNKNOWN", "direction": "LONG"}, {"date": "2026-07-06", "signal_type": "bottom", "entry_price": 373.8999938964844, "s_force": 0.18942844432414088, "peak_val": 0.28231038100037786, "signal_tier": "CONFIRMED", "action_pct": 1.0, "market_regime": "UNKNOWN", "direction": "LONG"}]}