{"ticker": "QQQ", "days": 120, "data": [{"date": "2026-03-02", "close_price": 606.6575317382812, "score": 0.0, "s_force": -0.009882189766493488, "s_div": 0.4863379207449765, "s_conc": 0.0, "er": null, "atr_pct": null}, {"date": "2026-03-03", "close_price": 600.1629028320312, "score": 0.0, "s_force": -0.4162820385878409, "s_div": 1.0, "s_conc": 0.0, "er": null, "atr_pct": null}, {"date": "2026-03-04", "close_price": 609.311279296875, "score": 0.17104222399054902, "s_force": 0.5083116815706892, "s_div": 0.05755414138277026, "s_conc": 0.0, "er": null, "atr_pct": null}, {"date": "2026-03-05", "close_price": 607.4755249023438, "score": 0.0, "s_force": -0.27700776211298345, "s_div": 0.0, "s_conc": 0.0, "er": null, "atr_pct": null}, {"date": "2026-03-06", "close_price": 598.337158203125, "score": 0.0, "s_force": -0.5434409598098445, "s_div": 0.0, "s_conc": 0.0, "er": null, "atr_pct": null}, {"date": "2026-03-09", "close_price": 606.3283081054688, "score": 0.0, "s_force": 0.7830643733258628, "s_div": 0.0, "s_conc": 0.0, "er": null, "atr_pct": null}, {"date": "2026-03-10", "close_price": 606.3383178710938, "score": 0.0, "s_force": 0.23216435373048983, "s_div": 0.0, "s_conc": 0.0, "er": null, "atr_pct": null}, {"date": "2026-03-11", "close_price": 606.2584838867188, "score": 0.18880867262973197, "s_force": 0.18666204603733894, "s_div": 0.1909799855781625, "s_conc": 0.0, "er": null, "atr_pct": null}, {"date": "2026-03-12", "close_price": 595.8530883789062, "score": 0.0, "s_force": -0.39394416390917086, "s_div": 0.6165329268415897, "s_conc": 0.0, "er": null, "atr_pct": null}, {"date": "2026-03-13", "close_price": 592.3213500976562, "score": 0.0457277593439588, "s_force": 0.12431305496406418, "s_div": 0.016820662763242972, "s_conc": 0.0, "er": null, "atr_pct": null}, {"date": "2026-03-16", "close_price": 598.9656982421875, "score": 0.0, "s_force": 0.5430897788131184, "s_div": 0.0, "s_conc": 0.0, "er": null, "atr_pct": null}, {"date": "2026-03-17", "close_price": 601.8887939453125, "score": 0.0, "s_force": 0.21242607541970984, "s_div": 0.0, "s_conc": 0.0, "er": null, "atr_pct": null}, {"date": "2026-03-18", "close_price": 593.4986572265625, "score": 0.0, "s_force": -0.3677694995702901, "s_div": 0.0, "s_conc": 0.0, "er": null, "atr_pct": null}, {"date": "2026-03-19", "close_price": 591.623046875, "score": 0.0, "s_force": 0.19073394676947406, "s_div": 0.0, "s_conc": 0.0, "er": null, "atr_pct": null}, {"date": "2026-03-20", "close_price": 580.6888427734375, "score": 0.0, "s_force": -0.5255022066592872, "s_div": 1.0, "s_conc": 0.0, "er": null, "atr_pct": null}, {"date": "2026-03-23", "close_price": 587.3545532226562, "score": 0.8288990521400762, "s_force": 0.9628206282215119, "s_div": 0.7136050251726065, "s_conc": 0.0, "er": null, "atr_pct": null}, {"date": "2026-03-24", "close_price": 583.3389282226562, "score": 0.2824337213572788, "s_force": 0.10656421240480095, "s_div": 0.7485515555326082, "s_conc": 0.0, "er": null, "atr_pct": null}, {"date": "2026-03-25", "close_price": 587.1747436523438, "score": 0.6100348623457321, "s_force": 0.4068789111550164, "s_div": 0.9146272344781078, "s_conc": 0.0, "er": null, "atr_pct": null}, {"date": "2026-03-26", "close_price": 573.1600952148438, "score": 0.0, "s_force": -0.8485175868300454, "s_div": 0.9344276566340647, "s_conc": 0.0, "er": null, "atr_pct": null}, {"date": "2026-03-27", "close_price": 561.9624633789062, "score": 0.0, "s_force": -0.3789325827349413, "s_div": 1.0, "s_conc": 0.0, "er": null, "atr_pct": null}, {"date": "2026-03-30", "close_price": 557.6671752929688, "score": 0.40655148437047867, "s_force": 0.16528410944383956, "s_div": 1.0, "s_conc": 0.0, "er": null, "atr_pct": null}, {"date": "2026-03-31", "close_price": 576.54638671875, "score": 0.8196271186164276, "s_force": 1.0, "s_div": 0.6717886135714674, "s_conc": 0.0, "er": null, "atr_pct": null}, {"date": "2026-04-01", "close_price": 583.6685791015625, "score": 0.4862184655823404, "s_force": 0.277686478011891, "s_div": 0.8513500475998047, "s_conc": 0.0, "er": null, "atr_pct": null}, {"date": "2026-04-02", "close_price": 584.3378295898438, "score": 0.0, "s_force": -0.1099888879885543, "s_div": 0.24666826760618377, "s_conc": 0.0, "er": null, "atr_pct": null}, {"date": "2026-04-06", "close_price": 587.85400390625, "score": 0.0, "s_force": -0.08507734377517541, "s_div": 0.0, "s_conc": 0.0, "er": null, "atr_pct": null}, {"date": "2026-04-07", "close_price": 587.9439086914062, "score": 0.0, "s_force": -0.25457558017445914, "s_div": 0.0, "s_conc": 0.0, "er": null, "atr_pct": null}, {"date": "2026-04-08", "close_price": 605.4246826171875, "score": 0.0, "s_force": 0.5342762297548995, "s_div": 0.0, "s_conc": 0.0, "er": null, "atr_pct": null}, {"date": "2026-04-09", "close_price": 609.5202026367188, "score": 0.0, "s_force": -0.1336904373997763, "s_div": 0.0, "s_conc": 0.0, "er": null, "atr_pct": null}, {"date": "2026-04-10", "close_price": 610.3992309570312, "score": 0.0, "s_force": -0.25992587858456306, "s_div": 0.0, "s_conc": 0.0, "er": null, "atr_pct": null}, {"date": "2026-04-13", "close_price": 616.7122802734375, "score": -0.3551656805433871, "s_force": -0.12614266063584728, "s_div": -1.0, "s_conc": 0.0, "er": null, "atr_pct": null}, {"date": "2026-04-14", "close_price": 627.909912109375, "score": 0.0, "s_force": 0.0041530161867533374, "s_div": -0.6019558172802866, "s_conc": 0.0, "er": null, "atr_pct": null}, {"date": "2026-04-15", "close_price": 636.7003173828125, "score": -0.3311613816590472, "s_force": -0.1788920628289074, "s_div": -0.6130392761316392, "s_conc": 0.0, "er": null, "atr_pct": null}, {"date": "2026-04-16", "close_price": 639.7669067382812, "score": -0.6049734766091958, "s_force": -0.3659929074006171, "s_div": -1.0, "s_conc": 0.0, "er": null, "atr_pct": null}, {"date": "2026-04-17", "close_price": 648.1376953125, "score": -0.3107713712032131, "s_force": -0.09657884515952526, "s_div": -1.0, "s_conc": 0.0, "er": null, "atr_pct": null}, {"date": "2026-04-20", "close_price": 646.0799560546875, "score": -0.6357947187004981, "s_force": -0.40423492432744546, "s_div": -1.0, "s_conc": 0.0, "er": null, "atr_pct": null}, {"date": "2026-04-21", "close_price": 643.6226806640625, "score": -0.554457042735084, "s_force": -0.30742261223853473, "s_div": -1.0, "s_conc": 0.0, "er": null, "atr_pct": null}, {"date": "2026-04-22", "close_price": 654.390869140625, "score": 0.0, "s_force": 0.17298590710305253, "s_div": -1.0, "s_conc": 0.0, "er": null, "atr_pct": null}, {"date": "2026-04-23", "close_price": 650.7048950195312, "score": -0.6380336511139009, "s_force": -0.40708693995373496, "s_div": -1.0, "s_conc": 0.0, "er": null, "atr_pct": null}, {"date": "2026-04-24", "close_price": 663.1512451171875, "score": 0.0, "s_force": 0.35546970951835466, "s_div": -1.0, "s_conc": 0.0, "er": null, "atr_pct": null}, {"date": "2026-04-27", "close_price": 663.5008544921875, "score": -0.41542476314127424, "s_force": -0.1725777338309838, "s_div": -1.0, "s_conc": 0.0, "er": null, "atr_pct": null}, {"date": "2026-04-28", "close_price": 656.8281860351562, "score": -0.6051151465139238, "s_force": -0.36616434054056757, "s_div": -1.0, "s_conc": 0.0, "er": null, "atr_pct": null}, {"date": "2026-04-29", "close_price": 660.84375, "score": 0.0, "s_force": 0.11599240640691727, "s_div": -1.0, "s_conc": 0.0, "er": null, "atr_pct": null}, {"date": "2026-04-30", "close_price": 667.0069580078125, "score": 0.0, "s_force": 0.27231227625261895, "s_div": -1.0, "s_conc": 0.0, "er": null, "atr_pct": null}, {"date": "2026-05-01", "close_price": 673.4099731445312, "score": 0.0, "s_force": 0.1579375770215965, "s_div": -0.9331688598812704, "s_conc": 0.0, "er": null, "atr_pct": null}, {"date": "2026-05-04", "close_price": 672.141357421875, "score": -0.541154290687747, "s_force": -0.4613562989142467, "s_div": -0.6347544555454112, "s_conc": 0.0, "er": null, "atr_pct": null}, {"date": "2026-05-05", "close_price": 680.8617553710938, "score": 0.0, "s_force": 0.42262550270900695, "s_div": -0.9552695840531754, "s_conc": 0.0, "er": null, "atr_pct": null}, {"date": "2026-05-06", "close_price": 695.0062255859375, "score": 0.0, "s_force": 0.6231505323868051, "s_div": -1.0, "s_conc": 0.0, "er": null, "atr_pct": null}, {"date": "2026-05-07", "close_price": 694.1771240234375, "score": -0.6162739867528821, "s_force": -1.0, "s_div": -0.37979362674829154, "s_conc": 0.0, "er": null, "atr_pct": null}, {"date": "2026-05-08", "close_price": 710.44921875, "score": 0.0, "s_force": 0.8204891780501451, "s_div": -0.3062931427106326, "s_conc": 0.0, "er": null, "atr_pct": null}, {"date": "2026-05-11", "close_price": 712.5069580078125, "score": -0.49395875317504334, "s_force": -0.48299767966783075, "s_div": -0.5051685755634372, "s_conc": 0.0, "er": null, "atr_pct": null}, {"date": "2026-05-12", "close_price": 706.463623046875, "score": -0.7469418346925794, "s_force": -0.9607544789851459, "s_div": -0.5807124677714279, "s_conc": 0.0, "er": null, "atr_pct": null}, {"date": "2026-05-13", "close_price": 713.9254760742188, "score": 0.0, "s_force": 0.32741746912219916, "s_div": -0.7010001302885476, "s_conc": 0.0, "er": null, "atr_pct": null}, {"date": "2026-05-14", "close_price": 718.9998168945312, "score": 0.0, "s_force": 0.07377054817206129, "s_div": -0.725421527530946, "s_conc": 0.0, "er": null, "atr_pct": null}, {"date": "2026-05-15", "close_price": 708.1517944335938, "score": -0.6348671395464625, "s_force": -1.0, "s_div": -0.4030562848759074, "s_conc": 0.0, "er": null, "atr_pct": null}, {"date": "2026-05-18", "close_price": 705.1051025390625, "score": 0.0, "s_force": -0.10514812932238222, "s_div": 0.0, "s_conc": 0.0, "er": null, "atr_pct": null}, {"date": "2026-05-19", "close_price": 700.7599487304688, "score": 0.0, "s_force": -0.0806398157930137, "s_div": 0.0, "s_conc": 0.0, "er": null, "atr_pct": null}, {"date": "2026-05-20", "close_price": 712.3671875, "score": 0.0, "s_force": 0.9057175064987174, "s_div": 0.0, "s_conc": 0.0, "er": null, "atr_pct": null}, {"date": "2026-05-21", "close_price": 713.7256469726562, "score": 0.0, "s_force": 0.046306326843192004, "s_div": -0.5296290483259865, "s_conc": 0.0, "er": null, "atr_pct": null}, {"date": "2026-05-22", "close_price": 716.7523193359375, "score": 0.0, "s_force": 0.14615445814287564, "s_div": -0.6929895801236841, "s_conc": 0.0, "er": null, "atr_pct": null}, {"date": "2026-05-26", "close_price": 729.4783935546875, "score": 0.0, "s_force": 0.6047679535111318, "s_div": -0.41884861128858075, "s_conc": 0.0, "er": null, "atr_pct": null}, {"date": "2026-05-27", "close_price": 728.6492919921875, "score": -0.3930832144034395, "s_force": -0.29053334287487315, "s_div": -0.531830226151656, "s_conc": 0.0, "er": null, "atr_pct": null}, {"date": "2026-05-28", "close_price": 734.79248046875, "score": 0.0, "s_force": 0.15042998838651125, "s_div": -0.5711532159761357, "s_conc": 0.0, "er": null, "atr_pct": null}, {"date": "2026-05-29", "close_price": 737.49951171875, "score": -0.228933522713181, "s_force": -0.07326297409140163, "s_div": -0.715375788000089, "s_conc": 0.0, "er": null, "atr_pct": null}, {"date": "2026-06-01", "close_price": 741.9246826171875, "score": 0.0, "s_force": 0.05134501962337876, "s_div": -0.8171450646096945, "s_conc": 0.0, "er": null, "atr_pct": null}, {"date": "2026-06-02", "close_price": 745.3408813476562, "score": 0.0, "s_force": 0.004667839952267007, "s_div": -0.9125497020600823, "s_conc": 0.0, "er": null, "atr_pct": null}, {"date": "2026-06-03", "close_price": 743.39306640625, "score": -0.4097047622912304, "s_force": -0.28169991593985405, "s_div": -0.5958751946520037, "s_conc": 0.0, "er": null, "atr_pct": null}, {"date": "2026-06-04", "close_price": 739.7969970703125, "score": -0.33365289426241285, "s_force": -0.2384181048111385, "s_div": -0.46692869208850435, "s_conc": 0.0, "er": null, "atr_pct": null}, {"date": "2026-06-05", "close_price": 704.2860107421875, "score": 0.0, "s_force": -1.0, "s_div": 0.0, "s_conc": 0.0, "er": null, "atr_pct": null}, {"date": "2026-06-08", "close_price": 715.283935546875, "score": 0.0, "s_force": 0.24647345424384595, "s_div": 0.0, "s_conc": 0.0, "er": null, "atr_pct": null}, {"date": "2026-06-09", "close_price": 707.052978515625, "score": 0.0, "s_force": -0.7932116734436461, "s_div": 1.0, "s_conc": 0.0, "er": null, "atr_pct": null}, {"date": "2026-06-10", "close_price": 692.9285278320312, "score": 0.0, "s_force": -0.5315122025358096, "s_div": 0.4603254376266446, "s_conc": 0.0, "er": null, "atr_pct": null}, {"date": "2026-06-11", "close_price": 716.332763671875, "score": 0.7468649537414804, "s_force": 1.0, "s_div": 0.5578072591272637, "s_conc": 0.0, "er": null, "atr_pct": null}, {"date": "2026-06-12", "close_price": 720.5481567382812, "score": 0.37150118672261284, "s_force": 0.3722346462724256, "s_div": 0.3707691723980541, "s_conc": 0.0, "er": null, "atr_pct": null}, {"date": "2026-06-15", "close_price": 743.1832885742188, "score": 0.0, "s_force": 0.693486875046748, "s_div": 0.0, "s_conc": 0.0, "er": null, "atr_pct": null}, {"date": "2026-06-16", "close_price": 729.0587768554688, "score": 0.0, "s_force": -0.2131669117553785, "s_div": 0.0, "s_conc": 0.0, "er": null, "atr_pct": null}, {"date": "2026-06-17", "close_price": 721.7168579101562, "score": 0.0, "s_force": 0.07398156662230665, "s_div": -0.10541505416150497, "s_conc": 0.0, "er": null, "atr_pct": null}, {"date": "2026-06-18", "close_price": 739.8070068359375, "score": 0.0, "s_force": 0.6316106655559497, "s_div": 0.0, "s_conc": 0.0, "er": null, "atr_pct": null}, {"date": "2026-06-22", "close_price": 737.9500122070312, "score": 0.0, "s_force": 0.07706460837848862, "s_div": 0.0, "s_conc": 0.0, "er": null, "atr_pct": null}, {"date": "2026-06-23", "close_price": 713.6500244140625, "score": 0.0, "s_force": -0.3730632068206371, "s_div": 0.0, "s_conc": 0.0, "er": null, "atr_pct": null}, {"date": "2026-06-24", "close_price": 710.6199951171875, "score": 0.0, "s_force": 0.22236383148320696, "s_div": 0.0, "s_conc": 0.0, "er": null, "atr_pct": null}, {"date": "2026-06-25", "close_price": 716.3800048828125, "score": 0.37720612860823716, "s_force": 0.3387726472847384, "s_div": 0.41999985713139304, "s_conc": 0.0, "er": null, "atr_pct": null}, {"date": "2026-06-26", "close_price": 706.52001953125, "score": 0.0, "s_force": -0.036118732368575567, "s_div": 0.5638104875689951, "s_conc": 0.0, "er": null, "atr_pct": null}, {"date": "2026-06-29", "close_price": 724.0800170898438, "score": 0.2848419106133959, "s_force": 0.4133583484041778, "s_div": 0.19628226780739144, "s_conc": 0.0, "er": null, "atr_pct": null}], "signals": [{"date": "2026-03-23", "signal_type": "bottom", "entry_price": 588.0, "s_force": 0.9072890895363522, "peak_val": 0.8159159707228505, "signal_tier": "CONFIRMED", "action_pct": 1.0, "market_regime": null, "direction": "LONG"}, {"date": "2026-06-11", "signal_type": "bottom", "entry_price": 717.1199951171875, "s_force": 1.0, "peak_val": 0.6988543203171133, "signal_tier": "CONFIRMED", "action_pct": 1.0, "market_regime": "UNKNOWN", "direction": "LONG"}, {"date": "2026-06-25", "signal_type": "bottom", "entry_price": 716.3800048828125, "s_force": 0.33549008048094764, "peak_val": 0.36489391329754, "signal_tier": "CONFIRMED", "action_pct": 1.0, "market_regime": "UNKNOWN", "direction": "LONG"}]}