{"ticker": "VOO", "days": 120, "data": [{"date": "2025-12-01", "close_price": 623.7547607421875, "score": 0.0, "s_force": -0.4037039470171484, "s_div": 0.0, "s_conc": 0.0, "er": null, "atr_pct": null}, {"date": "2025-12-02", "close_price": 624.811767578125, "score": 0.0, "s_force": -0.08702382558494347, "s_div": 0.0, "s_conc": 0.0, "er": null, "atr_pct": null}, {"date": "2025-12-03", "close_price": 626.99560546875, "score": 0.0, "s_force": 0.020212307853852397, "s_div": 0.0, "s_conc": 0.0, "er": null, "atr_pct": null}, {"date": "2025-12-04", "close_price": 627.5240478515625, "score": 0.0, "s_force": -0.026157649693964318, "s_div": 0.0, "s_conc": 0.0, "er": null, "atr_pct": null}, {"date": "2025-12-05", "close_price": 628.7007446289062, "score": 0.0, "s_force": 0.03884071178135098, "s_div": -0.5971729363237059, "s_conc": 0.0, "er": null, "atr_pct": null}, {"date": "2025-12-08", "close_price": 626.8359985351562, "score": -0.22387506362890397, "s_force": -0.11238495298436747, "s_div": -0.4459675675783519, "s_conc": 0.0, "er": null, "atr_pct": null}, {"date": "2025-12-09", "close_price": 626.3274536132812, "score": 0.0, "s_force": 0.03816856613620913, "s_div": -0.15421304194776406, "s_conc": 0.0, "er": null, "atr_pct": null}, {"date": "2025-12-10", "close_price": 630.3759765625, "score": 0.0, "s_force": 0.36190358645291176, "s_div": 0.0, "s_conc": 0.0, "er": null, "atr_pct": null}, {"date": "2025-12-11", "close_price": 631.9216918945312, "score": 0.0, "s_force": 0.06592404898903563, "s_div": 0.0, "s_conc": 0.0, "er": null, "atr_pct": null}, {"date": "2025-12-12", "close_price": 625.1009521484375, "score": 0.0, "s_force": -0.5357713543266504, "s_div": 0.0, "s_conc": 0.0, "er": null, "atr_pct": null}, {"date": "2025-12-15", "close_price": 624.1935424804688, "score": 0.0, "s_force": 0.3576851837467749, "s_div": 0.0, "s_conc": 0.0, "er": null, "atr_pct": null}, {"date": "2025-12-16", "close_price": 622.448486328125, "score": 0.0, "s_force": 0.11624057504224222, "s_div": 0.0, "s_conc": 0.0, "er": null, "atr_pct": null}, {"date": "2025-12-17", "close_price": 615.6077880859375, "score": 0.0, "s_force": -0.33365327023110253, "s_div": 0.0, "s_conc": 0.0, "er": null, "atr_pct": null}, {"date": "2025-12-18", "close_price": 620.2546997070312, "score": 0.0, "s_force": 0.9151633388669601, "s_div": 0.0, "s_conc": 0.0, "er": null, "atr_pct": null}, {"date": "2025-12-19", "close_price": 625.7890014648438, "score": 0.0, "s_force": 0.6157864992510483, "s_div": -1.0, "s_conc": 0.0, "er": null, "atr_pct": null}, {"date": "2025-12-22", "close_price": 629.72998046875, "score": 0.0, "s_force": 0.2243899043393311, "s_div": -0.7729958124298579, "s_conc": 0.0, "er": null, "atr_pct": null}, {"date": "2025-12-23", "close_price": 632.6699829101562, "score": 0.0, "s_force": -0.09888538736712697, "s_div": 0.0, "s_conc": 0.0, "er": null, "atr_pct": null}, {"date": "2025-12-24", "close_price": 634.780029296875, "score": 0.0, "s_force": -0.17778475438078856, "s_div": 0.0, "s_conc": 0.0, "er": null, "atr_pct": null}, {"date": "2025-12-26", "close_price": 634.8400268554688, "score": 0.0, "s_force": -0.29024244041118896, "s_div": 0.0, "s_conc": 0.0, "er": null, "atr_pct": null}, {"date": "2025-12-29", "close_price": 632.5999755859375, "score": 0.0, "s_force": -0.4410269407409009, "s_div": 0.0, "s_conc": 0.0, "er": null, "atr_pct": null}, {"date": "2025-12-30", "close_price": 631.719970703125, "score": 0.0, "s_force": -0.2228827735840365, "s_div": 0.0, "s_conc": 0.0, "er": null, "atr_pct": null}, {"date": "2025-12-31", "close_price": 627.1300048828125, "score": 0.0, "s_force": -0.47819909074828, "s_div": 0.0, "s_conc": 0.0, "er": null, "atr_pct": null}, {"date": "2026-01-02", "close_price": 628.2999877929688, "score": 0.0, "s_force": 0.629922080974343, "s_div": 0.0, "s_conc": 0.0, "er": null, "atr_pct": null}, {"date": "2026-01-05", "close_price": 632.4600219726562, "score": 0.0, "s_force": 0.9678206884988121, "s_div": 0.0, "s_conc": 0.0, "er": null, "atr_pct": null}, {"date": "2026-01-06", "close_price": 636.2100219726562, "score": 0.15526468089554443, "s_force": 0.4389327661378544, "s_div": 0.05492212701665563, "s_conc": 0.0, "er": null, "atr_pct": null}, {"date": "2026-01-07", "close_price": 634.1699829101562, "score": 0.0, "s_force": -0.4118997086498942, "s_div": 0.0, "s_conc": 0.0, "er": null, "atr_pct": null}, {"date": "2026-01-08", "close_price": 634.0599975585938, "score": 0.0, "s_force": -0.14996938617077726, "s_div": 0.0, "s_conc": 0.0, "er": null, "atr_pct": null}, {"date": "2026-01-09", "close_price": 638.3099975585938, "score": 0.0, "s_force": 0.19770714739571882, "s_div": -0.2170912619336852, "s_conc": 0.0, "er": null, "atr_pct": null}, {"date": "2026-01-12", "close_price": 639.3400268554688, "score": -0.24834167801544849, "s_force": -0.2552657968993167, "s_div": -0.2416053767824379, "s_conc": 0.0, "er": null, "atr_pct": null}, {"date": "2026-01-13", "close_price": 638.030029296875, "score": -0.4089709195992552, "s_force": -0.4695555462638309, "s_div": -0.35620325307345646, "s_conc": 0.0, "er": null, "atr_pct": null}, {"date": "2026-01-14", "close_price": 634.9400024414062, "score": -0.5135970738931449, "s_force": -0.556529639554353, "s_div": -0.47397647054849895, "s_conc": 0.0, "er": null, "atr_pct": null}, {"date": "2026-01-15", "close_price": 636.6199951171875, "score": 0.0, "s_force": 0.016217065754594237, "s_div": -0.7711195763019602, "s_conc": 0.0, "er": null, "atr_pct": null}, {"date": "2026-01-16", "close_price": 636.0900268554688, "score": -0.4003518757026624, "s_force": -0.20999919186901053, "s_div": -0.7632487675410559, "s_conc": 0.0, "er": null, "atr_pct": null}, {"date": "2026-01-20", "close_price": 623.1500244140625, "score": 0.0, "s_force": -1.0, "s_div": 0.0, "s_conc": 0.0, "er": null, "atr_pct": null}, {"date": "2026-01-21", "close_price": 630.2899780273438, "score": 0.0, "s_force": 0.8128041949342056, "s_div": 0.0, "s_conc": 0.0, "er": null, "atr_pct": null}, {"date": "2026-01-22", "close_price": 633.5700073242188, "score": 0.0, "s_force": 0.3146513353330542, "s_div": 0.0, "s_conc": 0.0, "er": null, "atr_pct": null}, {"date": "2026-01-23", "close_price": 633.8300170898438, "score": 0.0, "s_force": 0.051022648150041566, "s_div": -0.39053419110693893, "s_conc": 0.0, "er": null, "atr_pct": null}, {"date": "2026-01-26", "close_price": 637.0900268554688, "score": 0.0, "s_force": 0.27889503460679654, "s_div": 0.0, "s_conc": 0.0, "er": null, "atr_pct": null}, {"date": "2026-01-27", "close_price": 639.7000122070312, "score": 0.0, "s_force": 0.1471325611149901, "s_div": 0.0, "s_conc": 0.0, "er": null, "atr_pct": null}, {"date": "2026-01-28", "close_price": 639.5999755859375, "score": 0.0, "s_force": -0.04517437148431342, "s_div": 0.0, "s_conc": 0.0, "er": null, "atr_pct": null}, {"date": "2026-01-29", "close_price": 638.27001953125, "score": 0.0, "s_force": -0.12388929827483752, "s_div": 0.0, "s_conc": 0.0, "er": null, "atr_pct": null}, {"date": "2026-01-30", "close_price": 636.219970703125, "score": 0.0, "s_force": -0.11672430522261062, "s_div": 0.0, "s_conc": 0.0, "er": null, "atr_pct": null}, {"date": "2026-02-02", "close_price": 639.6799926757812, "score": 0.0, "s_force": 0.3750699487390102, "s_div": 0.0, "s_conc": 0.0, "er": null, "atr_pct": null}, {"date": "2026-02-03", "close_price": 634.1500244140625, "score": -0.4041600490706677, "s_force": -0.5438192057822219, "s_div": -0.3003670034600026, "s_conc": 0.0, "er": null, "atr_pct": null}, {"date": "2026-02-04", "close_price": 630.9099731445312, "score": 0.0, "s_force": -0.10622759399127614, "s_div": 0.0, "s_conc": 0.0, "er": null, "atr_pct": null}, {"date": "2026-02-05", "close_price": 623.0999755859375, "score": 0.0, "s_force": -0.5271666036637747, "s_div": 0.0, "s_conc": 0.0, "er": null, "atr_pct": null}, {"date": "2026-02-06", "close_price": 635.239990234375, "score": 0.43122151318800156, "s_force": 1.0, "s_div": 0.1859519934361498, "s_conc": 0.0, "er": null, "atr_pct": null}, {"date": "2026-02-09", "close_price": 638.22998046875, "score": 0.16202581341112363, "s_force": 0.3489099919470611, "s_div": 0.07524107883823351, "s_conc": 0.0, "er": null, "atr_pct": null}, {"date": "2026-02-10", "close_price": 636.4400024414062, "score": 0.0, "s_force": -0.23103351360605115, "s_div": 0.508674658757934, "s_conc": 0.0, "er": null, "atr_pct": null}, {"date": "2026-02-11", "close_price": 636.3499755859375, "score": 0.0, "s_force": -0.13765608684975142, "s_div": 0.0, "s_conc": 0.0, "er": null, "atr_pct": null}, {"date": "2026-02-12", "close_price": 626.489990234375, "score": 0.0, "s_force": -0.6607938784787923, "s_div": 0.0, "s_conc": 0.0, "er": null, "atr_pct": null}, {"date": "2026-02-13", "close_price": 626.8900146484375, "score": 0.0, "s_force": 0.14574718451658994, "s_div": 0.0, "s_conc": 0.0, "er": null, "atr_pct": null}, {"date": "2026-02-17", "close_price": 627.989990234375, "score": 0.22532036469902336, "s_force": 0.11079643314225517, "s_div": 0.45822112958200173, "s_conc": 0.0, "er": null, "atr_pct": null}, {"date": "2026-02-18", "close_price": 631.1500244140625, "score": 0.0, "s_force": 0.1640596241045323, "s_div": 0.0, "s_conc": 0.0, "er": null, "atr_pct": null}, {"date": "2026-02-19", "close_price": 629.530029296875, "score": 0.0, "s_force": -0.09890897090443646, "s_div": 0.0, "s_conc": 0.0, "er": null, "atr_pct": null}, {"date": "2026-02-20", "close_price": 634.02001953125, "score": 0.0, "s_force": 0.24958833264004993, "s_div": 0.0, "s_conc": 0.0, "er": null, "atr_pct": null}, {"date": "2026-02-23", "close_price": 627.6300048828125, "score": 0.0, "s_force": -0.7693501155378063, "s_div": 0.0, "s_conc": 0.0, "er": null, "atr_pct": null}, {"date": "2026-02-24", "close_price": 632.2100219726562, "score": 0.08708574203674296, "s_force": 0.0740755771126742, "s_div": 0.1023809298786083, "s_conc": 0.0, "er": null, "atr_pct": null}, {"date": "2026-02-25", "close_price": 637.530029296875, "score": 0.30318986743085974, "s_force": 0.0919240957127423, "s_div": 1.0, "s_conc": 0.0, "er": null, "atr_pct": null}, {"date": "2026-02-26", "close_price": 633.9500122070312, "score": 0.0, "s_force": -0.5188399045016487, "s_div": 0.6343603424955259, "s_conc": 0.0, "er": null, "atr_pct": null}, {"date": "2026-02-27", "close_price": 631.0399780273438, "score": 0.0, "s_force": -0.2631361103667043, "s_div": 0.4416512675485145, "s_conc": 0.0, "er": null, "atr_pct": null}, {"date": "2026-03-02", "close_price": 631.280029296875, "score": 0.13787798583138164, "s_force": 0.04304584159914596, "s_div": 0.44163009179720253, "s_conc": 0.0, "er": null, "atr_pct": null}, {"date": "2026-03-03", "close_price": 625.719970703125, "score": 0.0, "s_force": -0.5923801605336548, "s_div": 1.0, "s_conc": 0.0, "er": null, "atr_pct": null}, {"date": "2026-03-04", "close_price": 630.1799926757812, "score": 0.441874995240926, "s_force": 0.4782352830056225, "s_div": 0.40827918465579377, "s_conc": 0.0, "er": null, "atr_pct": null}, {"date": "2026-03-05", "close_price": 626.8099975585938, "score": 0.0, "s_force": -0.21722109437026524, "s_div": 0.2243155474860666, "s_conc": 0.0, "er": null, "atr_pct": null}, {"date": "2026-03-06", "close_price": 618.4299926757812, "score": 0.0, "s_force": -0.3711587504320933, "s_div": 0.101715862833122, "s_conc": 0.0, "er": null, "atr_pct": null}, {"date": "2026-03-09", "close_price": 623.7999877929688, "score": 0.7040725373186716, "s_force": 0.9451549063959057, "s_div": 0.5244834835557698, "s_conc": 0.0, "er": null, "atr_pct": null}, {"date": "2026-03-10", "close_price": 622.719970703125, "score": 0.23834081522552522, "s_force": 0.05680634420236796, "s_div": 1.0, "s_conc": 0.0, "er": null, "atr_pct": null}, {"date": "2026-03-11", "close_price": 622.030029296875, "score": 0.14230706451996766, "s_force": 0.07899849647754673, "s_div": 0.2563504562146464, "s_conc": 0.0, "er": null, "atr_pct": null}, {"date": "2026-03-12", "close_price": 612.5, "score": 0.0, "s_force": -0.8817004166913731, "s_div": 1.0, "s_conc": 0.0, "er": null, "atr_pct": null}, {"date": "2026-03-13", "close_price": 609.0900268554688, "score": 0.6971576929960271, "s_force": 0.4860288489035428, "s_div": 1.0, "s_conc": 0.0, "er": null, "atr_pct": null}, {"date": "2026-03-16", "close_price": 615.1900024414062, "score": 0.5852488091522802, "s_force": 0.8640802716002455, "s_div": 0.3963939229625442, "s_conc": 0.0, "er": null, "atr_pct": null}, {"date": "2026-03-17", "close_price": 616.8900146484375, "score": 0.3612163035243128, "s_force": 0.24042915479688773, "s_div": 0.5426846758330718, "s_conc": 0.0, "er": null, "atr_pct": null}, {"date": "2026-03-18", "close_price": 608.3800048828125, "score": 0.0, "s_force": -0.7021533321312146, "s_div": 1.0, "s_conc": 0.0, "er": null, "atr_pct": null}, {"date": "2026-03-19", "close_price": 606.75, "score": 0.0, "s_force": -0.02214593060991442, "s_div": 1.0, "s_conc": 0.0, "er": null, "atr_pct": null}, {"date": "2026-03-20", "close_price": 597.9400024414062, "score": 0.0, "s_force": -0.6586266537798142, "s_div": 1.0, "s_conc": 0.0, "er": null, "atr_pct": null}, {"date": "2026-03-23", "close_price": 604.4299926757812, "score": 1.0, "s_force": 1.0, "s_div": 1.0, "s_conc": 0.0, "er": null, "atr_pct": null}, {"date": "2026-03-24", "close_price": 602.3800048828125, "score": 0.3603508055846743, "s_force": 0.12985270308552374, "s_div": 1.0, "s_conc": 0.0, "er": null, "atr_pct": null}, {"date": "2026-03-25", "close_price": 605.6599731445312, "score": 0.7316193126700794, "s_force": 0.5352668186718395, "s_div": 1.0, "s_conc": 0.0, "er": null, "atr_pct": null}, {"date": "2026-03-26", "close_price": 594.9199829101562, "score": 0.0, "s_force": -0.13515476451967598, "s_div": 0.9909627470896534, "s_conc": 0.0, "er": null, "atr_pct": null}, {"date": "2026-03-27", "close_price": 582.9600219726562, "score": 0.0, "s_force": -0.20105108264875407, "s_div": 1.0, "s_conc": 0.0, "er": null, "atr_pct": null}], "signals": [{"date": "2026-03-23", "signal_type": "bottom", "entry_price": 604.4299926757812, "s_force": 1.0, "peak_val": 1.0, "signal_tier": "CONFIRMED", "action_pct": 1.0, "market_regime": null, "direction": "LONG"}]}