[{"ticker": "TSLA", "sector": "Tech", "date": "2026-06-17", "close_price": 396.3800048828125, "prev_close": 404.6600036621094, "change_pct": -2.05, "score": -0.1262573593361536, "s_force": -0.1851788524724076, "er": null, "atr_pct": null, "recent_signal": null}, {"ticker": "PLTR", "sector": "Tech", "date": "2026-06-17", "close_price": 130.6300048828125, "prev_close": 133.25, "change_pct": -1.97, "score": 0.0, "s_force": -0.10802889625557684, "er": null, "atr_pct": null, "recent_signal": {"direction": "LONG", "peak_date": "2026-04-10", "tier": "CONFIRMED", "s_force": 0.8607261596764973, "peak_val": 0.9277532859960655, "age_days": 68}}, {"ticker": "NVDA", "sector": "Tech", "date": "2026-06-17", "close_price": 204.64999389648438, "prev_close": 207.41000366210938, "change_pct": -1.33, "score": 0.034567742373590234, "s_force": 0.022222047286912235, "er": null, "atr_pct": null, "recent_signal": {"direction": "LONG", "peak_date": "2026-06-11", "tier": "CONFIRMED", "s_force": 0.5060484677333987, "peak_val": 0.43693558615172595, "age_days": 6}}, {"ticker": "AVGO", "sector": "Tech", "date": "2026-06-17", "close_price": 392.8999938964844, "prev_close": 376.7099914550781, "change_pct": 4.3, "score": 0.3794610719476496, "s_force": 0.3482283320435617, "er": null, "atr_pct": null, "recent_signal": {"direction": "LONG", "peak_date": "2026-06-11", "tier": "CONFIRMED", "s_force": 0.6828211717476275, "peak_val": 0.7274020293455201, "age_days": 6}}, {"ticker": "AMZN", "sector": "Tech", "date": "2026-06-17", "close_price": 237.5, "prev_close": 246.0, "change_pct": -3.46, "score": 0.0, "s_force": -0.6177648919780039, "er": null, "atr_pct": null, "recent_signal": {"direction": "LONG", "peak_date": "2026-06-04", "tier": "CONFIRMED", "s_force": 0.9620927560554362, "peak_val": 0.2509113326823622, "age_days": 13}}, {"ticker": "GOOGL", "sector": "Tech", "date": "2026-06-17", "close_price": 363.7900085449219, "prev_close": 373.25, "change_pct": -2.53, "score": 0.0, "s_force": -0.5146693644504883, "er": null, "atr_pct": null, "recent_signal": {"direction": "LONG", "peak_date": "2026-06-03", "tier": "CONFIRMED", "s_force": 0.5139997230600916, "peak_val": 0.7169377400165872, "age_days": 14}}, {"ticker": "JOBY", "sector": "Growth", "date": "2026-06-17", "close_price": 9.390000343322754, "prev_close": 9.34000015258789, "change_pct": 0.54, "score": 0.2635718839799507, "s_force": 0.1845459108591767, "er": null, "atr_pct": null, "recent_signal": null}, {"ticker": "HIMS", "sector": "Growth", "date": "2026-06-17", "close_price": 31.889999389648438, "prev_close": 31.469999313354492, "change_pct": 1.33, "score": -0.4579666655286777, "s_force": -0.30885173405573213, "er": null, "atr_pct": null, "recent_signal": {"direction": "LONG", "peak_date": "2026-05-19", "tier": "CONFIRMED", "s_force": 0.3185421684894169, "peak_val": 0.35679398820444214, "age_days": 29}}, {"ticker": "TEM", "sector": "Growth", "date": "2026-06-17", "close_price": 48.790000915527344, "prev_close": 50.560001373291016, "change_pct": -3.5, "score": 0.0, "s_force": -0.1766825544910742, "er": null, "atr_pct": null, "recent_signal": null}, {"ticker": "RKLB", "sector": "Growth", "date": "2026-06-17", "close_price": 107.9800033569336, "prev_close": 104.62999725341797, "change_pct": 3.2, "score": 0.163715539240631, "s_force": 0.19936653239464236, "er": null, "atr_pct": null, "recent_signal": null}, {"ticker": "COIN", "sector": "Fintech", "date": "2026-06-17", "close_price": 164.9149932861328, "prev_close": 169.27000427246094, "change_pct": -2.57, "score": 0.0, "s_force": -0.21424667843689363, "er": null, "atr_pct": null, "recent_signal": null}, {"ticker": "HOOD", "sector": "Fintech", "date": "2026-06-17", "close_price": 105.19999694824219, "prev_close": 96.70999908447266, "change_pct": 8.78, "score": 0.0, "s_force": 1.0, "er": null, "atr_pct": null, "recent_signal": null}, {"ticker": "IONQ", "sector": "Quantum", "date": "2026-06-17", "close_price": 54.689998626708984, "prev_close": 56.060001373291016, "change_pct": -2.44, "score": 0.0, "s_force": 0.07153160599928438, "er": null, "atr_pct": null, "recent_signal": null}, {"ticker": "PL", "sector": "Space", "date": "2026-06-17", "close_price": 28.219999313354492, "prev_close": 28.209999084472656, "change_pct": 0.04, "score": 0.0, "s_force": -0.07592471791200471, "er": null, "atr_pct": null, "recent_signal": {"direction": "LONG", "peak_date": "2026-06-08", "tier": "CONFIRMED", "s_force": 1.0, "peak_val": 0.808940399352403, "age_days": 9}}, {"ticker": "ASTS", "sector": "Space", "date": "2026-06-17", "close_price": 85.43000030517578, "prev_close": 82.25, "change_pct": 3.87, "score": 0.0, "s_force": 0.3460460929065009, "er": null, "atr_pct": null, "recent_signal": {"direction": "LONG", "peak_date": "2026-04-02", "tier": "CONFIRMED", "s_force": 0.7037987958691032, "peak_val": 0.23411817464408224, "age_days": 76}}, {"ticker": "CRCL", "sector": "Growth", "date": "2026-06-17", "close_price": 80.58999633789062, "prev_close": 79.72000122070312, "change_pct": 1.09, "score": 0.376437049541268, "s_force": 0.4366191582291954, "er": null, "atr_pct": null, "recent_signal": null}, {"ticker": "SOFI", "sector": "Fintech", "date": "2026-06-17", "close_price": 17.420000076293945, "prev_close": 17.709999084472656, "change_pct": -1.64, "score": 0.0, "s_force": -0.5925075362875738, "er": null, "atr_pct": null, "recent_signal": null}, {"ticker": "VOO", "sector": "Index", "date": "2026-06-17", "close_price": 681.4099731445312, "prev_close": 689.75, "change_pct": -1.21, "score": 0.0, "s_force": -0.35681363497190843, "er": null, "atr_pct": null, "recent_signal": {"direction": "LONG", "peak_date": "2026-03-23", "tier": "CONFIRMED", "s_force": 1.0, "peak_val": 1.0, "age_days": 86}}, {"ticker": "QQQ", "sector": "Index", "date": "2026-06-17", "close_price": 722.510009765625, "prev_close": 729.8599853515625, "change_pct": -1.01, "score": 0.0, "s_force": 0.059247920579453744, "er": null, "atr_pct": null, "recent_signal": {"direction": "LONG", "peak_date": "2026-06-11", "tier": "CONFIRMED", "s_force": 1.0, "peak_val": 0.6988543203171133, "age_days": 6}}]