[{"ticker": "TSLA", "sector": "Tech", "date": "2026-04-27", "close_price": 378.6700134277344, "prev_close": 376.29998779296875, "change_pct": 0.63, "score": 0.0, "s_force": -0.021523978230144406, "er": null, "atr_pct": null, "recent_signal": null}, {"ticker": "PLTR", "sector": "Tech", "date": "2026-04-27", "close_price": 143.10000610351562, "prev_close": 143.08999633789062, "change_pct": 0.01, "score": 0.0, "s_force": -0.16190647920480342, "er": null, "atr_pct": null, "recent_signal": {"direction": "LONG", "peak_date": "2026-04-10", "tier": "CONFIRMED", "s_force": 0.8607261596764973, "peak_val": 0.9277532859960655}}, {"ticker": "NVDA", "sector": "Tech", "date": "2026-04-27", "close_price": 216.61000061035156, "prev_close": 208.27000427246094, "change_pct": 4.0, "score": 0.0, "s_force": 0.6112932905951813, "er": null, "atr_pct": null, "recent_signal": {"direction": "LONG", "peak_date": "2026-03-31", "tier": "CONFIRMED", "s_force": 1.0, "peak_val": 0.6940157795359037}}, {"ticker": "AVGO", "sector": "Tech", "date": "2026-04-27", "close_price": 418.20001220703125, "prev_close": 422.760009765625, "change_pct": -1.08, "score": -0.5831771253955192, "s_force": -0.34009555958458115, "er": null, "atr_pct": null, "recent_signal": null}, {"ticker": "AMZN", "sector": "Tech", "date": "2026-04-27", "close_price": 261.1199951171875, "prev_close": 263.989990234375, "change_pct": -1.09, "score": -0.7162963128626965, "s_force": -0.5130804078206939, "er": null, "atr_pct": null, "recent_signal": {"direction": "LONG", "peak_date": "2026-03-31", "tier": "CONFIRMED", "s_force": 1.0, "peak_val": 0.5146957777693537}}, {"ticker": "GOOGL", "sector": "Tech", "date": "2026-04-27", "close_price": 350.3399963378906, "prev_close": 344.3999938964844, "change_pct": 1.72, "score": 0.0, "s_force": 0.1458416623876352, "er": null, "atr_pct": null, "recent_signal": null}, {"ticker": "JOBY", "sector": "Growth", "date": "2026-04-27", "close_price": 9.039999961853027, "prev_close": 8.5, "change_pct": 6.35, "score": 0.1748924543630216, "s_force": 1.0, "er": null, "atr_pct": null, "recent_signal": null}, {"ticker": "HIMS", "sector": "Growth", "date": "2026-04-27", "close_price": 29.389999389648438, "prev_close": 30.559999465942383, "change_pct": -3.83, "score": 0.0, "s_force": -0.07341529928041751, "er": null, "atr_pct": null, "recent_signal": null}, {"ticker": "TEM", "sector": "Growth", "date": "2026-04-27", "close_price": 52.68000030517578, "prev_close": 52.119998931884766, "change_pct": 1.07, "score": 0.0, "s_force": 0.041249661823759685, "er": null, "atr_pct": null, "recent_signal": null}, {"ticker": "RKLB", "sector": "Growth", "date": "2026-04-27", "close_price": 82.29000091552734, "prev_close": 79.68000030517578, "change_pct": 3.28, "score": 0.0, "s_force": 0.17089494775380007, "er": null, "atr_pct": null, "recent_signal": null}, {"ticker": "COIN", "sector": "Fintech", "date": "2026-04-27", "close_price": 196.67999267578125, "prev_close": 199.77000427246094, "change_pct": -1.55, "score": -0.10844174597764823, "s_force": -0.015546950993208951, "er": null, "atr_pct": null, "recent_signal": null}, {"ticker": "HOOD", "sector": "Fintech", "date": "2026-04-27", "close_price": 83.94999694824219, "prev_close": 84.70999908447266, "change_pct": -0.9, "score": -0.13315389780012177, "s_force": -0.020742789998626485, "er": null, "atr_pct": null, "recent_signal": null}, {"ticker": "IONQ", "sector": "Quantum", "date": "2026-04-27", "close_price": 43.84000015258789, "prev_close": 42.689998626708984, "change_pct": 2.69, "score": 0.0, "s_force": 0.23267983313436474, "er": null, "atr_pct": null, "recent_signal": null}, {"ticker": "PL", "sector": "Space", "date": "2026-04-27", "close_price": 35.45000076293945, "prev_close": 35.439998626708984, "change_pct": 0.03, "score": -0.20380987426435762, "s_force": -0.07634150159139265, "er": null, "atr_pct": null, "recent_signal": {"direction": "LONG", "peak_date": "2026-04-01", "tier": "CONFIRMED", "s_force": 0.6936236851133546, "peak_val": 0.16606232850138342}}, {"ticker": "ASTS", "sector": "Space", "date": "2026-04-27", "close_price": 77.19999694824219, "prev_close": 76.4000015258789, "change_pct": 1.05, "score": 0.0, "s_force": 0.2489976175783452, "er": null, "atr_pct": null, "recent_signal": {"direction": "LONG", "peak_date": "2026-04-02", "tier": "CONFIRMED", "s_force": 0.7037987958691032, "peak_val": 0.23411817464408224}}, {"ticker": "CRCL", "sector": "Growth", "date": "2026-04-27", "close_price": 95.44000244140625, "prev_close": 99.66000366210938, "change_pct": -4.23, "score": -0.09528003706997903, "s_force": -0.07257488312359228, "er": null, "atr_pct": null, "recent_signal": null}, {"ticker": "SOFI", "sector": "Fintech", "date": "2026-04-27", "close_price": 18.760000228881836, "prev_close": 18.440000534057617, "change_pct": 1.74, "score": 0.0, "s_force": 0.3518581964117827, "er": null, "atr_pct": null, "recent_signal": null}, {"ticker": "VOO", "sector": "Index", "date": "2026-04-27", "close_price": 657.5, "prev_close": 656.4199829101562, "change_pct": 0.16, "score": -0.4439366374624824, "s_force": -0.19707973808149554, "er": null, "atr_pct": null, "recent_signal": {"direction": "LONG", "peak_date": "2026-03-23", "tier": "CONFIRMED", "s_force": 1.0, "peak_val": 1.0}}, {"ticker": "QQQ", "sector": "Index", "date": "2026-04-27", "close_price": 664.22998046875, "prev_close": 663.8800048828125, "change_pct": 0.05, "score": -0.4154253078261914, "s_force": -0.1725781863824859, "er": null, "atr_pct": null, "recent_signal": {"direction": "LONG", "peak_date": "2026-03-23", "tier": "CONFIRMED", "s_force": 0.9072890895363522, "peak_val": 0.8159159707228505}}]