[{"ticker": "TSLA", "sector": "Tech", "date": "2026-04-29", "close_price": 372.79998779296875, "prev_close": 376.0199890136719, "change_pct": -0.86, "score": -0.21521338232105827, "s_force": -0.10535978937023353, "er": null, "atr_pct": null, "recent_signal": null}, {"ticker": "PLTR", "sector": "Tech", "date": "2026-04-29", "close_price": 137.97000122070312, "prev_close": 141.17999267578125, "change_pct": -2.27, "score": -0.03898980724751416, "s_force": -0.12978999210088332, "er": null, "atr_pct": null, "recent_signal": {"direction": "LONG", "peak_date": "2026-04-10", "tier": "CONFIRMED", "s_force": 0.8607261596764973, "peak_val": 0.9277532859960655}}, {"ticker": "NVDA", "sector": "Tech", "date": "2026-04-29", "close_price": 209.25, "prev_close": 213.1699981689453, "change_pct": -1.84, "score": -0.7421747860810705, "s_force": -0.5508234130944827, "er": null, "atr_pct": null, "recent_signal": {"direction": "LONG", "peak_date": "2026-03-31", "tier": "CONFIRMED", "s_force": 1.0, "peak_val": 0.6940157795359037}}, {"ticker": "AVGO", "sector": "Tech", "date": "2026-04-29", "close_price": 405.45001220703125, "prev_close": 399.8299865722656, "change_pct": 1.41, "score": 0.0, "s_force": 0.14001341888041044, "er": null, "atr_pct": null, "recent_signal": null}, {"ticker": "AMZN", "sector": "Tech", "date": "2026-04-29", "close_price": 263.0400085449219, "prev_close": 259.70001220703125, "change_pct": 1.29, "score": 0.0, "s_force": 0.38245606598565535, "er": null, "atr_pct": null, "recent_signal": {"direction": "LONG", "peak_date": "2026-03-31", "tier": "CONFIRMED", "s_force": 1.0, "peak_val": 0.5146957777693537}}, {"ticker": "GOOGL", "sector": "Tech", "date": "2026-04-29", "close_price": 349.94000244140625, "prev_close": 349.7799987792969, "change_pct": 0.05, "score": -0.376593166967226, "s_force": -0.15387353537325504, "er": null, "atr_pct": null, "recent_signal": null}, {"ticker": "JOBY", "sector": "Growth", "date": "2026-04-29", "close_price": 8.699999809265137, "prev_close": 8.930000305175781, "change_pct": -2.58, "score": 0.0, "s_force": -0.6344670196593137, "er": null, "atr_pct": null, "recent_signal": null}, {"ticker": "HIMS", "sector": "Growth", "date": "2026-04-29", "close_price": 26.329999923706055, "prev_close": 27.90999984741211, "change_pct": -5.66, "score": -0.2838463336814758, "s_force": -0.1312224414376807, "er": null, "atr_pct": null, "recent_signal": null}, {"ticker": "TEM", "sector": "Growth", "date": "2026-04-29", "close_price": 50.02000045776367, "prev_close": 51.099998474121094, "change_pct": -2.11, "score": 0.0, "s_force": 0.026485166413479373, "er": null, "atr_pct": null, "recent_signal": null}, {"ticker": "RKLB", "sector": "Growth", "date": "2026-04-29", "close_price": 77.0199966430664, "prev_close": 78.58999633789062, "change_pct": -2.0, "score": -0.06207771866793153, "s_force": -0.005790184513105663, "er": null, "atr_pct": null, "recent_signal": null}, {"ticker": "COIN", "sector": "Fintech", "date": "2026-04-29", "close_price": 181.72999572753906, "prev_close": 194.10000610351562, "change_pct": -6.37, "score": -0.2125578054569437, "s_force": -0.5131423831906983, "er": null, "atr_pct": null, "recent_signal": null}, {"ticker": "HOOD", "sector": "Fintech", "date": "2026-04-29", "close_price": 71.19999694824219, "prev_close": 82.06999969482422, "change_pct": -13.24, "score": 0.0, "s_force": -1.0, "er": null, "atr_pct": null, "recent_signal": null}, {"ticker": "IONQ", "sector": "Quantum", "date": "2026-04-29", "close_price": 42.11000061035156, "prev_close": 43.08000183105469, "change_pct": -2.25, "score": 0.0, "s_force": 0.0656898986919388, "er": null, "atr_pct": null, "recent_signal": null}, {"ticker": "PL", "sector": "Space", "date": "2026-04-29", "close_price": 34.08000183105469, "prev_close": 35.029998779296875, "change_pct": -2.71, "score": -0.298228918447233, "s_force": -0.11711316731165662, "er": null, "atr_pct": null, "recent_signal": {"direction": "LONG", "peak_date": "2026-04-01", "tier": "CONFIRMED", "s_force": 0.6936236851133546, "peak_val": 0.16606232850138342}}, {"ticker": "ASTS", "sector": "Space", "date": "2026-04-29", "close_price": 69.8499984741211, "prev_close": 71.87999725341797, "change_pct": -2.82, "score": 0.0, "s_force": 0.1475576677217121, "er": null, "atr_pct": null, "recent_signal": {"direction": "LONG", "peak_date": "2026-04-02", "tier": "CONFIRMED", "s_force": 0.7037987958691032, "peak_val": 0.23411817464408224}}, {"ticker": "CRCL", "sector": "Growth", "date": "2026-04-29", "close_price": 95.55999755859375, "prev_close": 94.3499984741211, "change_pct": 1.28, "score": 0.0, "s_force": 0.17115152033578168, "er": null, "atr_pct": null, "recent_signal": null}, {"ticker": "SOFI", "sector": "Fintech", "date": "2026-04-29", "close_price": 15.524999618530273, "prev_close": 18.360000610351562, "change_pct": -15.44, "score": 0.0, "s_force": -1.0, "er": null, "atr_pct": null, "recent_signal": null}, {"ticker": "VOO", "sector": "Index", "date": "2026-04-29", "close_price": 654.239990234375, "prev_close": 654.260009765625, "change_pct": -0.0, "score": 0.0, "s_force": 0.0626097689132829, "er": null, "atr_pct": null, "recent_signal": {"direction": "LONG", "peak_date": "2026-03-23", "tier": "CONFIRMED", "s_force": 1.0, "peak_val": 1.0}}, {"ticker": "QQQ", "sector": "Index", "date": "2026-04-29", "close_price": 661.5700073242188, "prev_close": 657.5499877929688, "change_pct": 0.61, "score": 0.0, "s_force": 0.11599402779796278, "er": null, "atr_pct": null, "recent_signal": {"direction": "LONG", "peak_date": "2026-03-23", "tier": "CONFIRMED", "s_force": 0.9072890895363522, "peak_val": 0.8159159707228505}}]