{"ticker": "PLTR", "similar": [{"id": 18, "ticker": "AVGO", "peak_date": "2026-06-11", "peak_val": 0.7274020293455201, "close_price": 385.57000732421875, "s_force": 0.6828211717476275, "s_div": 0.7748935360948983, "dd_pct": 0.1993479629958924, "duration": 9, "similarity": 0.9782, "return_5d": null, "return_20d": null, "return_90d": null, "max_dd_90d": null, "outcome": null}, {"id": 14, "ticker": "GOOGL", "peak_date": "2026-06-03", "peak_val": 0.7169377400165872, "close_price": 358.989990234375, "s_force": 0.5139997230600916, "s_div": 1.0, "dd_pct": 0.1083652213301365, "duration": 1, "similarity": 0.9706, "return_5d": -0.73, "return_20d": null, "return_90d": null, "max_dd_90d": null, "outcome": null}, {"id": 16, "ticker": "PL", "peak_date": "2026-06-08", "peak_val": 0.808940399352403, "close_price": 32.7400016784668, "s_force": 1.0, "s_div": 0.6543845697044254, "dd_pct": 0.36303500570942904, "duration": 1, "similarity": 0.9641, "return_5d": -6.6, "return_20d": null, "return_90d": null, "max_dd_90d": null, "outcome": null}, {"id": 1, "ticker": "NVDA", "peak_date": "2026-03-16", "peak_val": 0.36686794106219744, "close_price": 183.22000122070312, "s_force": 0.48377815935919927, "s_div": 0.278210339957251, "dd_pct": null, "duration": 1, "similarity": 0.9433, "return_5d": -4.25, "return_20d": 7.13, "return_90d": null, "max_dd_90d": null, "outcome": null}, {"id": 17, "ticker": "NVDA", "peak_date": "2026-06-11", "peak_val": 0.43693558615172595, "close_price": 204.8699951171875, "s_force": 0.5060484677333987, "s_div": 0.37726170242319707, "dd_pct": 0.12993653489440282, "duration": 1, "similarity": 0.935, "return_5d": null, "return_20d": null, "return_90d": null, "max_dd_90d": null, "outcome": null}]}